{
  "name": "MangaBaka",
  "identifier": "dev.oazzies.mangabaka",
  "headerURL": "REPLACE_WITH_HEADER_IMAGE_URL",
  "website": "https://github.com/Oazzies/MangaBaka-App",
  "iconURL": "https://raw.githubusercontent.com/Oazzies/MangaBaka-App/refs/heads/main/assets/mangabaka512.png",
  "subtitle": "Official app for the largest manga and sorts database",
  "description": "This is the official sideloading source for MangaBaka.\n\nFor full details, check the GitHub repository:\nhttps://github.com/Oazzies/MangaBaka-App",
  "tintColor": "0a0a0a",
  "apps": [
    {
      "beta": false,
      "name": "MangaBaka",
      "bundleIdentifier": "dev.oazzies.mangabaka",
      "developerName": "Oazzies",
      "subtitle": "Official app for the largest manga and sorts database",
      "version": "0.0.0",
      "versionDate": "1970-01-01T00:00:00Z",
      "versionDescription": "Placeholder entry. This is overwritten automatically the first time the Update Sideloading Source workflow runs after a release is published.",
      "downloadURL": "",
      "localizedDescription": "MangaBaka is the official app for the largest manga and sorts database.",
      "iconURL": "https://raw.githubusercontent.com/Oazzies/MangaBaka-App/refs/heads/main/assets/mangabaka512.png",
      "tintColor": "0a0a0a",
      "category": "entertainment",
      "size": 0,
      "screenshotURLs": [],
      "versions": [],
      "appPermissions": {
        "entitlements": [],
        "privacy": []
      }
    }
  ],
  "news": []
}
